mfont/__init__.py
mfont/load_font.py
mfont/fonts/FangZhengHeiTiJianTi-1.ttf
mfont/fonts/LXGWWenKaiGBLite-Regular.ttf
mfont/fonts/RomanSong.ttf
mfont-0.1.2.dist-info/METADATA
mfont-0.1.2.dist-info/WHEEL
mfont-0.1.2.dist-info/top_level.txt
mfont-0.1.2.dist-info/RECORD
